catfish_sim/__init__.py
catfish_sim/agents.py
catfish_sim/compatibility.py
catfish_sim/matchers.py
catfish_sim/strategies.py
catfish_sim/utils.py
catfish_sim/data/LLCP2022_sex_age_height_bmi.csv
catfish_sim-0.2.0.dist-info/METADATA
catfish_sim-0.2.0.dist-info/WHEEL
catfish_sim-0.2.0.dist-info/licenses/LICENSE
catfish_sim-0.2.0.dist-info/RECORD
