Metadata-Version: 2.3
Name: catfish-sim
Version: 0.2.0
Summary: A multiagent online dating simulation framework.
Project-URL: Homepage, https://github.com/ozgunozankilic/catfish-sim
Project-URL: Repository, https://github.com/ozgunozankilic/catfish-sim
Project-URL: Issues, https://github.com/ozgunozankilic/catfish-sim/issues
Project-URL: Changelog, https://github.com/ozgunozankilic/catfish-sim/blob/main/CHANGELOG.md
Author-email: Oz Kilic <ozgunozankilic@gmail.com>
License:                     GNU GENERAL PUBLIC LICENSE
License-File: LICENSE
Keywords: agent-based modeling,multiagent,online dating,simulation,social simulation
Classifier: Development Status :: 4 - Beta
Classifier: License :: OSI Approved :: GNU General Public License v3 (GPLv3)
Classifier: Operating System :: OS Independent
Classifier: Programming Language :: Python :: 3
Classifier: Programming Language :: Python :: 3.6
Classifier: Programming Language :: Python :: 3.7
Classifier: Programming Language :: Python :: 3.8
Classifier: Programming Language :: Python :: 3.9
Classifier: Programming Language :: Python :: 3.10
Classifier: Programming Language :: Python :: 3.11
Classifier: Topic :: Games/Entertainment :: Simulation
Classifier: Topic :: Scientific/Engineering
Classifier: Topic :: Sociology
Classifier: Topic :: Software Development
Classifier: Topic :: Software Development :: Libraries
Classifier: Topic :: Software Development :: Libraries :: Python Modules
Requires-Python: >=3.6
Requires-Dist: numpy>=1.23.3
Requires-Dist: pandas>=1.5.0
Requires-Dist: scikit-learn>=1.3.2
Requires-Dist: scipy>=1.8.1
Requires-Dist: trueskill>=0.4.5
Provides-Extra: dev
Requires-Dist: pytest>=7.4.3; extra == 'dev'
